ccpayments_gateway/__init__.py
ccpayments_gateway/client.py
ccpayments_gateway/webhooks.py
ccpayments_gateway-0.1.0.dist-info/METADATA
ccpayments_gateway-0.1.0.dist-info/WHEEL
ccpayments_gateway-0.1.0.dist-info/top_level.txt
ccpayments_gateway-0.1.0.dist-info/RECORD
